ailola.py
ailola-0.9.23.dist-info/METADATA
ailola-0.9.23.dist-info/WHEEL
ailola-0.9.23.dist-info/entry_points.txt
ailola-0.9.23.dist-info/top_level.txt
ailola-0.9.23.dist-info/RECORD
